{"pk":25377,"name":"techforum-hd-2","org":11438,"site":4,"workspace":{"pk":12180,"name":"DevOps-Workspace","slug":"devops-workspace","org":11438,"is_default":false,"is_pinned":null,"created":"2018-10-04T14:50:40.966473Z"},"instance_id":"netkunphf8","provider":"aws","provider_keyset":37632,"provider_keyset_name":"netapp-kubernetes-user","region":"us-east-1","platform":"coreos","channel":"stable","state":"draft","build_version":"1.0","project_id":"","owner":11214,"user_ssh_keyset":37619,"user_ssh_keyset_name":"Default SPC SSH Keypair","etcd_type":"classic","provider_network_id":"vpc-0c20454fd2c589945","provider_network_cidr":"172.16.0.0/16","provider_subnet_id":"subnet-000b4821d29589423","provider_subnet_cidr":"172.16.1.0/24","provider_balancer_id":null,"provider_resource_group":null,"config":{"enable_experimental_features":true},"layout":{},"solutions":[{"pk":48311,"name":"Helm Tiller","instance_id":"solvpjjoo6","cluster":25377,"solution":"helm_tiller","installer":"ansible_custom","keyset":null,"keyset_name":"","version":"latest","version_migrations":[],"state":"draft","url":"","username":"","password":"","max_nodes":null,"git_repo":"","git_path":"","initial":true,"config":{},"extra_data":{},"created":"2019-09-27T10:33:37.124434Z","updated":"2019-09-27T10:33:37.124461Z","is_deleteable":false}],"features":[],"follower":{},"notified":false,"created":"2019-09-27T10:33:33.024984Z","updated":"2019-09-27T10:33:37.041393Z","k8s_version":"v1.15.3","k8s_dashboard_enabled":true,"k8s_rbac_enabled":true,"k8s_etcd_operator_installed":false,"k8s_dashboard_installed":false,"k8s_pod_cidr":"10.2.0.0/16","k8s_service_cidr":"10.3.0.0/24","is_kubeconfig_available":false,"kubeconfig_path":"/orgs/11438/clusters/25377/kubeconfig","node_count":3,"master_count":1,"master_size":"t2.medium","worker_count":2,"worker_size":"nodepool-dependent","master_root_disk_size":null,"worker_root_disk_size":null,"image":"ami-06d2804068b372d32","zone":"us-east-1a","is_k8s_available":false,"is_failed":false,"federation_role":null,"k8s_etcd_cluster":null,"is_etcd_host":false,"version_migrations":[],"istio_mesh_member":null,"owner_detail":"Simon Heger"}